leuci_pol/__init__.py
leuci_pol/interpolator.py
leuci_pol/invariantmaker.py
leuci_pol/iteration.py
leuci_pol/iv1.py
leuci_pol/iv2.py
leuci_pol/iv3.py
leuci_pol/iv5.py
leuci_pol/scoring.py
leuci_pol/xinterp_help.py
leuci_pol/xinterpolation.py
leuci_pol/xinvariant.py
leuci_pol/xthevenaz.py
leuci_pol-0.0.53.dist-info/LICENSE
leuci_pol-0.0.53.dist-info/METADATA
leuci_pol-0.0.53.dist-info/WHEEL
leuci_pol-0.0.53.dist-info/top_level.txt
leuci_pol-0.0.53.dist-info/RECORD
